{"ibum90":"$2y$10$tp4gJdM2TIlQe8Wo5Ef7Uu.BUKnxXf6UBM3AeJAffI0EExaFqs.hS","ibum91":"$2y$10$fNnDl\/1hanCWvjTc9tmsW.mCL\/poEJClLvrmvE1AdKswhUJTOaNie","nee":"$2y$10$.JwvplUNYg37yM47OzqGsO.TCD1rEdTEb2Yllfpr2xdq0DeizbMRS","aqua":"$2y$10$VR98zwCkQQSu3fKz\/p0H0uKaCG7kRCIHAvTC3zqQR8aIsbfLUT6J2","nini":"$2y$10$ixFO9l42ncUILPmGuJai1.\/AIbT\/KN6YDmHjgGnvSLUhG1qRi9mTy","memey":"$2y$10$g6sm1nFMF0hA5.EnMNLnoOprhFqKEuTIxxQLJAhU6QOVtdEkoFkUK","wowi":"$2y$10$UPp1U455bpM.HCc74DaqwO6MQ\/.wIYLiYAWWb6fA\/sF7ekKbe\/eEC","nubus2":"$2y$10$X1jUUWygjCDDS9yTe9J7XeRdrfuz7bKV952oCmr5meNH9PjEulmEW","siswa1":"$2y$10$KI0op7P2d7Ytmv35DUP\/2ePw1FJ5yXTWY4M0w8bAxEgMAqT.wCHwy","neenee":"$2y$10$TBg1yyeo8JMuC9gpyr9Kk.qfNeYyOSsV377GB6MlSy\/jWdWs8mmTm"}